django_dart_sass/__init__.py
django_dart_sass/apps.py
django_dart_sass/cli.py
django_dart_sass/compressor.py
django_dart_sass/decorators.py
django_dart_sass/functions.py
django_dart_sass/importers.py
django_dart_sass/registry.py
django_dart_sass-0.1.0.dist-info/METADATA
django_dart_sass-0.1.0.dist-info/WHEEL
django_dart_sass-0.1.0.dist-info/entry_points.txt
django_dart_sass-0.1.0.dist-info/RECORD
