Metadata-Version: 2.4
Name: django-dart-sass
Version: 0.1.0
Summary: Django integration for Python Dart Sass with django-compressor support
Project-URL: Homepage, https://github.com/hmcqueen/django-dart-sass
Project-URL: Documentation, https://github.com/hmcqueen/django-dart-sass#readme
Project-URL: Repository, https://github.com/hmcqueen/django-dart-sass
Project-URL: Bug Tracker, https://github.com/hmcqueen/django-dart-sass/issues
Project-URL: Changelog, https://github.com/hmcqueen/django-dart-sass/blob/main/CHANGELOG.md
Author-email: Harvey McQueen <hmcqueen@gmail.com>
Maintainer-email: Harvey McQueen <hmcqueen@gmail.com>
License-Expression: MIT
Keywords: compressor,css,django,embedded,sass,scss
Classifier: Development Status :: 3 - Alpha
Classifier: Framework :: Django
Classifier: Framework :: Django :: 3.2
Classifier: Framework :: Django :: 4.0
Classifier: Framework :: Django :: 4.1
Classifier: Framework :: Django :: 4.2
Classifier: Framework :: Django :: 5.0
Classifier: Framework :: Django :: 5.1
Classifier: Framework :: Django :: 5.2
Classifier: Intended Audience :: Developers
Classifier: License :: OSI Approved :: MIT License
Classifier: Operating System :: OS Independent
Classifier: Programming Language :: Python :: 3
Classifier: Programming Language :: Python :: 3.10
Classifier: Programming Language :: Python :: 3.11
Classifier: Programming Language :: Python :: 3.12
Classifier: Topic :: Internet :: WWW/HTTP
Classifier: Topic :: Software Development :: Libraries :: Python Modules
Classifier: Topic :: Text Processing :: Markup
Requires-Python: >=3.10
Requires-Dist: django<6.0,>=3.2
Requires-Dist: python-dart-sass>=0.1.0
Provides-Extra: compressor
Requires-Dist: django-compressor>=4.0; extra == 'compressor'
Provides-Extra: dev
Requires-Dist: black>=22.0.0; extra == 'dev'
Requires-Dist: django-compressor>=4.0; extra == 'dev'
Requires-Dist: isort>=5.10.0; extra == 'dev'
Requires-Dist: pytest-cov>=4.0.0; extra == 'dev'
Requires-Dist: pytest-django>=4.5.0; extra == 'dev'
Requires-Dist: pytest>=7.0.0; extra == 'dev'
Requires-Dist: ruff>=0.1.0; extra == 'dev'
